tinyloop/__init__.py
tinyloop/py.typed
tinyloop/types.py
tinyloop/features/__init__.py
tinyloop/features/function_calling.py
tinyloop/features/vision.py
tinyloop/inference/__init__.py
tinyloop/inference/base.py
tinyloop/inference/litellm.py
tinyloop/modules/__init__.py
tinyloop/modules/base_loop.py
tinyloop/modules/generate.py
tinyloop/modules/tool_loop.py
tinyloop/utils/mlflow.py
tinyloop/utils/observability.py
tinyloop/utils/prompt_renderer.py
tinyloop-0.1.35.dist-info/METADATA
tinyloop-0.1.35.dist-info/WHEEL
tinyloop-0.1.35.dist-info/licenses/LICENSE
tinyloop-0.1.35.dist-info/RECORD
