Metadata-Version: 2.4
Name: tinyloop
Version: 0.1.35
Summary: A super lightweight library for LLM-based applications
Project-URL: repository, https://github.com/fmeiraf/tinyloop
Author-email: Fernando Meira <fmeira.filho@gmail.com>
License: MIT
License-File: LICENSE
Requires-Python: >=3.11
Requires-Dist: jinja2>=3.1.6
Requires-Dist: langfuse>=3.3.2
Requires-Dist: litellm>=1.75.9
Requires-Dist: mlflow>=3.3.1
Requires-Dist: pillow>=11.3.0
Requires-Dist: pydantic>=2.11.7
